{
  "product_line": "KubeStash",
  "release": "v2026.4.27",
  "release_date": "2026-04-22T09:54:58.274140392Z",
  "release_project_url": "https://github.com/kubestash/CHANGELOG",
  "docs_url": "https://kubestash.com/docs/v2026.4.27",
  "kubernetes_version": "1.28+",
  "projects": [
    {
      "url": "github.com/kubestash/apimachinery",
      "releases": [
        {
          "tag": "v0.27.0",
          "commits": [
            {
              "SHA": "15ef11cd",
              "Subject": "Bug fix for AzureFederatedTokenFile check (#228)"
            },
            {
              "SHA": "81617867",
              "Subject": "Configure dependabot refresh schedule (#227)"
            },
            {
              "SHA": "df6625c5",
              "Subject": "Cleanup CVEs"
            },
            {
              "SHA": "edb0aa0a",
              "Subject": "Cleanup CVEs"
            },
            {
              "SHA": "471e1d5b",
              "Subject": "Add Cloud Annotations for restore session (#226)"
            },
            {
              "SHA": "0532bb60",
              "Subject": "Fix vendor for restic plugins (#222)"
            },
            {
              "SHA": "ca5351d9",
              "Subject": "Add credential manger and  cloud annotation methods (#220)"
            },
            {
              "SHA": "65ad1567",
              "Subject": "Replace azidentity master with beta version (#221)"
            },
            {
              "SHA": "0b73be0b",
              "Subject": "Update blob & annotations for azure identity binding (#217)"
            },
            {
              "SHA": "d6aff5e5",
              "Subject": "Test against k8s 1.35 (#218)"
            },
            {
              "SHA": "d106d3eb",
              "Subject": "Inject S3 credential Manually for IRSA"
            },
            {
              "SHA": "aa7a3c4f",
              "Subject": "Add ClickHouse Stats"
            },
            {
              "SHA": "d1da8aec",
              "Subject": "Update aws annotations for seed role (#214)"
            },
            {
              "SHA": "e1b88a14",
              "Subject": "Update KubeDB and cert-manager (#211)"
            }
          ]
        }
      ]
    },
    {
      "url": "github.com/kubestash/kubedump",
      "releases": [
        {
          "tag": "v0.26.0",
          "commits": [
            {
              "SHA": "1ad012f3",
              "Subject": "Prepare for release v0.26.0 (#87)"
            },
            {
              "SHA": "8070801d",
              "Subject": "Bump RESTIC_VERSION to 0.18.1-20260421 (#86)"
            },
            {
              "SHA": "7d5d93d3",
              "Subject": "Prepare for release v0.26.0-rc.0 (#84)"
            },
            {
              "SHA": "25d059a6",
              "Subject": "Incorporate changes for the AWS credless feature (#83)"
            }
          ]
        }
      ]
    },
    {
      "url": "github.com/kubestash/kubestash",
      "releases": [
        {
          "tag": "v0.27.0",
          "commits": [
            {
              "SHA": "e1f0ea20",
              "Subject": "Prepare for release v0.27.0 (#355)"
            },
            {
              "SHA": "293d9ee8",
              "Subject": "Bump RESTIC_VERSION to 0.18.1-20260421 (#354)"
            },
            {
              "SHA": "1cb336cd",
              "Subject": "Set Condition if retention policy Job failed (#353)"
            },
            {
              "SHA": "4dce7391",
              "Subject": "Prepare for release v0.27.0-rc.0 (#351)"
            },
            {
              "SHA": "144181ed",
              "Subject": "Update apimachinery and unsuspend job for azure identity binding (#346)"
            },
            {
              "SHA": "4054ab20",
              "Subject": "Update job controller to unsuspend job for AWS credless"
            },
            {
              "SHA": "084529b5",
              "Subject": "Give endpointslices permissions (#341)"
            }
          ]
        }
      ]
    },
    {
      "url": "github.com/kubestash/manifest",
      "releases": [
        {
          "tag": "v0.19.0",
          "commits": [
            {
              "SHA": "ea51d5ed",
              "Subject": "Prepare for release v0.19.0 (#65)"
            },
            {
              "SHA": "2d51179e",
              "Subject": "Bump RESTIC_VERSION to 0.18.1-20260421 (#64)"
            },
            {
              "SHA": "a2927d49",
              "Subject": "Prepare for release v0.19.0-rc.0 (#62)"
            },
            {
              "SHA": "42ac18cf",
              "Subject": "Incorporate changes for the AWS credless feature (#61)"
            }
          ]
        }
      ]
    },
    {
      "url": "github.com/kubestash/pvc",
      "releases": [
        {
          "tag": "v0.26.0",
          "commits": [
            {
              "SHA": "53a4a0e9",
              "Subject": "Prepare for release v0.26.0 (#87)"
            },
            {
              "SHA": "f84c778f",
              "Subject": "Bump RESTIC_VERSION to 0.18.1-20260421 (#86)"
            },
            {
              "SHA": "de896841",
              "Subject": "Prepare for release v0.26.0-rc.0 (#83)"
            },
            {
              "SHA": "b4565d9e",
              "Subject": "Incorporate changes for aws credless operation (#82)"
            }
          ]
        }
      ]
    },
    {
      "url": "github.com/kubestash/vault",
      "releases": [
        {
          "tag": "v0.1.0",
          "commits": [
            {
              "SHA": "9e64034",
              "Subject": "Prepare for release v0.1.0 (#6)"
            },
            {
              "SHA": "0d0b854",
              "Subject": "Bump RESTIC_VERSION to 0.18.1-20260421 (#5)"
            },
            {
              "SHA": "855f3cd",
              "Subject": "Change Repo Name to Vault Only"
            },
            {
              "SHA": "f83f17b",
              "Subject": "Add vault restic backup / restore support for Postgres, Raft"
            }
          ]
        }
      ]
    },
    {
      "url": "github.com/kubestash/volume-snapshotter",
      "releases": [
        {
          "tag": "v0.26.0",
          "commits": [
            {
              "SHA": "a15200f3",
              "Subject": "Prepare for release v0.26.0 (#73)"
            },
            {
              "SHA": "d782a3b8",
              "Subject": "Prepare for release v0.26.0-rc.0 (#72)"
            }
          ]
        }
      ]
    },
    {
      "url": "github.com/kubestash/workload",
      "releases": [
        {
          "tag": "v0.26.0",
          "commits": [
            {
              "SHA": "124338d3",
              "Subject": "Prepare for release v0.26.0 (#96)"
            },
            {
              "SHA": "f5f20801",
              "Subject": "Bump RESTIC_VERSION to 0.18.1-20260421 (#95)"
            },
            {
              "SHA": "a6863790",
              "Subject": "Prepare for release v0.26.0-rc.0 (#93)"
            },
            {
              "SHA": "fd2954c8",
              "Subject": "Incorporate changes for the AWS credless feature"
            }
          ]
        }
      ]
    }
  ]
}
